modbuspy/ADU/RTUADU.py
modbuspy/ADU/TCPADU.py
modbuspy/ADU/__init__.py
modbuspy/Client/RTUClient.py
modbuspy/Client/TCPClient.py
modbuspy/Client/__init__.py
modbuspy/PDU/ClientPDU.py
modbuspy/PDU/ServerPDU.py
modbuspy/PDU/__init__.py
modbuspy/Server/RTUServer.py
modbuspy/Server/Slave.py
modbuspy/Server/TCPServer.py
modbuspy/Server/__init__.py
modbuspy/__init__.py
modbuspy-0.1.5.dist-info/LICENSE
modbuspy-0.1.5.dist-info/METADATA
modbuspy-0.1.5.dist-info/WHEEL
modbuspy-0.1.5.dist-info/RECORD
