Metadata-Version: 2.1
Name: modbuspy
Version: 0.1.5
Summary: 
Home-page: https://github.com/ulfaric/ModbusPy
License: CC-BY-NC-ND-4.0
Author: ulfaric
Author-email: ryf0510@live.com
Requires-Python: >=3.12,<4.0
Classifier: License :: Other/Proprietary License
Classifier: Programming Language :: Python :: 3
Classifier: Programming Language :: Python :: 3.12
Classifier: Programming Language :: Python :: 3.13
Requires-Dist: colorlog (>=6.8.2,<7.0.0)
Requires-Dist: pyserial-asyncio (>=0.6,<0.7)
Requires-Dist: pyyaml (>=6.0.2,<7.0.0)
Project-URL: Repository, https://github.com/ulfaric/ModbusPy
